surak/__init__.py
surak/engine.py
surak/evaluator.py
surak/exceptions.py
surak/operators.py
surak/plugin.py
surak/policy.py
surak/cli/__init__.py
surak/cli/commands.py
surak/cli/main.py
surak/dev_server/__init__.py
surak/dev_server/app.py
surak/plugins/__init__.py
surak/plugins/azure.py
surak/plugins/bitbucket.py
surak/plugins/github.py
surak/plugins/gitlab.py
surak-0.1.0.dist-info/METADATA
surak-0.1.0.dist-info/WHEEL
surak-0.1.0.dist-info/entry_points.txt
surak-0.1.0.dist-info/licenses/LICENSE
surak-0.1.0.dist-info/RECORD
